cfpackages/__init__.py
cfpackages/file_utils.py
cfpackages/http_utils.py
cfpackages/logger_formatter.py
cfpackages/text_ui.py
cfpackages-0.1.2.dist-info/licenses/LICENSE
cfpackages-0.1.2.dist-info/METADATA
cfpackages-0.1.2.dist-info/WHEEL
cfpackages-0.1.2.dist-info/top_level.txt
cfpackages-0.1.2.dist-info/RECORD
