Metadata-Version: 2.4
Name: cfpackages
Version: 0.1.2
Summary: 一个供我自己使用的实用的 python 第三方库
Author-email: chengfeng3012 <chengfeng3012@163.com>
Requires-Python: >=3.6
License-File: LICENSE
Requires-Dist: colorama
Requires-Dist: prompt_toolkit
Requires-Dist: questionary
Dynamic: license-file
